mirrorit/__init__.py
mirrorit/cli.py
mirrorit-1.0.2.dist-info/licenses/LICENSE
mirrorit-1.0.2.dist-info/METADATA
mirrorit-1.0.2.dist-info/WHEEL
mirrorit-1.0.2.dist-info/entry_points.txt
mirrorit-1.0.2.dist-info/top_level.txt
mirrorit-1.0.2.dist-info/RECORD
