Metadata-Version: 2.4
Name: mirrorit
Version: 1.0.2
Summary: For mirroring text.
Author: Lunethra
License-Expression: MIT
Project-URL: Homepage, https://github.com/Lunethra/mirrorit
Requires-Python: >=3.5
License-File: LICENSE
Requires-Dist: typer[all]
Requires-Dist: rich
Dynamic: license-file
